{"data":{"allMarkdownRemark":{"totalCount":1,"edges":[{"node":{"fields":{"slug":"/blog/frohe-weihnachten"},"excerpt":"Frohe Weihnachten! \nIch wünsche dir ruhige, besinnliche und fröhliche Weihnachtsfeiertage. Tanke Kraft für die Aufgaben im neuen Jahr und lass den Alltagsstress mal mit einem guten Buch beiseite. Auch ich möchte dir ein Geschenk machen: Ich biete drei meiner Lieblingsbilder aus der  #Proprius  Reihe…","timeToRead":1,"frontmatter":{"title":"Frohe Weihnachten","tags":["Weihnachten"],"date":"24. Dezember 2017","category":"Freebie"}}}]}},"pageContext":{"jsonName":"tags-weihnachten-22b","internalComponentName":"ComponentTagsWeihnachten","path":"/tags/weihnachten/","component":"D:/git/gatsby/testing_showcase/aleman2/src/templates/tag.jsx","componentChunkName":"component---src-templates-tag-jsx","context":{"tag":"Weihnachten"},"updatedAt":1536356119752,"pluginCreator___NODE":"Plugin default-site-plugin","pluginCreatorId":"Plugin default-site-plugin","componentPath":"D:/git/gatsby/testing_showcase/aleman2/src/templates/tag.jsx","tag":"Weihnachten"}}